amsphyslab_tools/__init__.py
amsphyslab_tools/tools_cli.py
amsphyslab_tools-0.3.0.dist-info/entry_points.txt
amsphyslab_tools-0.3.0.dist-info/LICENSE
amsphyslab_tools-0.3.0.dist-info/WHEEL
amsphyslab_tools-0.3.0.dist-info/METADATA
amsphyslab_tools-0.3.0.dist-info/RECORD
